nvelope/__init__.py
nvelope/conversions.py
nvelope/nvelope.py
nvelope-1.1.1.dist-info/LICENSE
nvelope-1.1.1.dist-info/WHEEL
nvelope-1.1.1.dist-info/METADATA
nvelope-1.1.1.dist-info/RECORD
