Metadata-Version: 2.1
Name: nvelope
Version: 1.1.1
Summary: Painless JSON marshalling and unmarshalling
Home-page: https://github.com/monomonedula/nvelope
License: MIT
Keywords: serialization,deserialization,json,marshalling,unmarshalling,utility
Author: monomonedula
Author-email: valh@tuta.io
Requires-Python: >=3.8,<4.0
Classifier: License :: OSI Approved :: MIT License
Classifier: Programming Language :: Python :: 3
Classifier: Programming Language :: Python :: 3.10
Classifier: Programming Language :: Python :: 3.8
Classifier: Programming Language :: Python :: 3.9
Project-URL: Repository, https://github.com/monomonedula/nvelope
